pycmarkgfm-1.2.1.dist-info/LICENSE
pycmarkgfm-1.2.1.dist-info/top_level.txt
pycmarkgfm-1.2.1.dist-info/RECORD
pycmarkgfm-1.2.1.dist-info/METADATA
pycmarkgfm-1.2.1.dist-info/WHEEL
pycmarkgfm/_cmark.abi3.so
pycmarkgfm/cmark_module.h
pycmarkgfm/cmark.cffi.h
pycmarkgfm/options.py
pycmarkgfm/__init__.py
pycmarkgfm/build_cmark.py
pycmarkgfm/cmark.py
