Metadata-Version: 2.1
Name: pycmarkgfm
Version: 1.2.1
Summary: Bindings to GitHub's Flavored Markdown (cmark-gfm), with enhanced support for task lists.
Home-page: https://github.com/zopieux/pycmarkgfm
Author: Alexandre Macabies
Author-email: web@zopieux.com
Project-URL: Bug Reports, https://github.com/zopieux/pycmarkgfm/issues
Project-URL: Source, https://github.com/zopieux/pycmarkgfm
Classifier: Development Status :: 4 - Beta
Classifier: Intended Audience :: Developers
Classifier: Operating System :: MacOS :: MacOS X
Classifier: Operating System :: Microsoft :: Windows
Classifier: Operating System :: POSIX :: Linux
Classifier: License :: OSI Approved :: GNU General Public License v3 or later (GPLv3+)
Classifier: Programming Language :: Python :: 3
Classifier: Programming Language :: Python :: 3.7
Classifier: Programming Language :: Python :: 3.8
Classifier: Programming Language :: Python :: 3.9
Classifier: Programming Language :: Python :: 3.10
Classifier: Programming Language :: Python :: 3.11
License-File: LICENSE
Requires-Dist: cffi >=1.15.0
